paraxial/__about__.py
paraxial/__init__.py
paraxial/equations.py
paraxial/materials.py
paraxial/sources.py
paraxial/surfaces.py
paraxial-0.10.0.dist-info/METADATA
paraxial-0.10.0.dist-info/WHEEL
paraxial-0.10.0.dist-info/licenses/LICENSE
paraxial-0.10.0.dist-info/RECORD
