Metadata-Version: 2.1
Name: paraxial
Version: 0.10.0
Summary: A library for nontrivial paraxial optics calculations
Project-URL: Documentation, https://github.com/danieldmulkey/paraxial#readme
Project-URL: Issues, https://github.com/danieldmulkey/paraxial/issues
Project-URL: Source, https://github.com/danieldmulkey/paraxial
Author-email: danieldmulkey <danieldmulkey@users.noreply.github.com>
License-Expression: MIT
License-File: LICENSE
Classifier: Development Status :: 4 - Beta
Classifier: Programming Language :: Python
Classifier: Programming Language :: Python :: 3.9
Classifier: Programming Language :: Python :: 3.10
Classifier: Programming Language :: Python :: 3.11
Classifier: Programming Language :: Python :: Implementation :: CPython
Classifier: Programming Language :: Python :: Implementation :: PyPy
Requires-Python: >=3.9
Requires-Dist: numpy
Requires-Dist: sympy
